datalabel
