Metadata-Version: 2.1
Name: datalabel
Version: 0.1.5
Summary: quickly and effortlessly edit your dataframes without having to write any code. Its intuitive interface makes it ideal for both experienced data professionals and those new to data editing.
Author: TitanLabs
Author-email: product@titanlabs.co
